{
  "node": {
    "7f48ba0f67349b5555b761f395b55b64ee3700777a": {
      "workers": {
        "app/_not-found/page": {
          "moduleId": "[project]/.next-internal/server/app/_not-found/page/actions.js { ACTIONS_MODULE0 => \"[project]/node_modules/@clerk/nextjs/dist/esm/app-router/keyless-actions.js [app-rsc] (ecmascript)\", ACTIONS_MODULE1 => \"[project]/node_modules/@clerk/nextjs/dist/esm/app-router/server-actions.js [app-rsc] (ecmascript)\" } [app-rsc] (server actions loader, ecmascript)",
          "async": false
        }
      },
      "layer": {
        "app/_not-found/page": "action-browser"
      }
    },
    "7f7daf4f1106fa5ed85d96ccfcbee1139a76340f69": {
      "workers": {
        "app/_not-found/page": {
          "moduleId": "[project]/.next-internal/server/app/_not-found/page/actions.js { ACTIONS_MODULE0 => \"[project]/node_modules/@clerk/nextjs/dist/esm/app-router/keyless-actions.js [app-rsc] (ecmascript)\", ACTIONS_MODULE1 => \"[project]/node_modules/@clerk/nextjs/dist/esm/app-router/server-actions.js [app-rsc] (ecmascript)\" } [app-rsc] (server actions loader, ecmascript)",
          "async": false
        }
      },
      "layer": {
        "app/_not-found/page": "action-browser"
      }
    },
    "7f8f86695fa0eb59412fb98e3a7f26ece5d4ff5661": {
      "workers": {
        "app/_not-found/page": {
          "moduleId": "[project]/.next-internal/server/app/_not-found/page/actions.js { ACTIONS_MODULE0 => \"[project]/node_modules/@clerk/nextjs/dist/esm/app-router/keyless-actions.js [app-rsc] (ecmascript)\", ACTIONS_MODULE1 => \"[project]/node_modules/@clerk/nextjs/dist/esm/app-router/server-actions.js [app-rsc] (ecmascript)\" } [app-rsc] (server actions loader, ecmascript)",
          "async": false
        }
      },
      "layer": {
        "app/_not-found/page": "action-browser"
      }
    },
    "7ff7d760957fab854dcb97e20b03fcbd472aa5ac05": {
      "workers": {
        "app/_not-found/page": {
          "moduleId": "[project]/.next-internal/server/app/_not-found/page/actions.js { ACTIONS_MODULE0 => \"[project]/node_modules/@clerk/nextjs/dist/esm/app-router/keyless-actions.js [app-rsc] (ecmascript)\", ACTIONS_MODULE1 => \"[project]/node_modules/@clerk/nextjs/dist/esm/app-router/server-actions.js [app-rsc] (ecmascript)\" } [app-rsc] (server actions loader, ecmascript)",
          "async": false
        }
      },
      "layer": {
        "app/_not-found/page": "action-browser"
      }
    }
  },
  "edge": {}
}